unitconverterPy/__init__.py
unitconverterPy/converter.py
unitconverterpy-0.1.0.dist-info/METADATA
unitconverterpy-0.1.0.dist-info/WHEEL
unitconverterpy-0.1.0.dist-info/top_level.txt
unitconverterpy-0.1.0.dist-info/RECORD
