Metadata-Version: 2.1
Name: unitconverterpy
Version: 0.1.0
Summary: A library for unit conversion between various measurement units
Home-page: https://github.com/DinukChehara/pyconverter
Author: Dinuk Chehara
Author-email: dinukchehara24@gmail.com
Classifier: Programming Language :: Python :: 3
Classifier: License :: OSI Approved :: MIT License
Classifier: Operating System :: OS Independent
Requires-Python: >=3.6
